[
  {
    "time": 0,
    "count": 13
  },
  {
    "time": 10,
    "count": 31
  },
  {
    "time": 20,
    "count": 48
  },
  {
    "time": 30,
    "count": 46
  },
  {
    "time": 40,
    "count": 38
  },
  {
    "time": 50,
    "count": 27
  },
  {
    "time": 60,
    "count": 19
  },
  {
    "time": 70,
    "count": 33
  },
  {
    "time": 80,
    "count": 26
  },
  {
    "time": 90,
    "count": 30
  },
  {
    "time": 100,
    "count": 63
  },
  {
    "time": 110,
    "count": 121
  },
  {
    "time": 120,
    "count": 86
  },
  {
    "time": 130,
    "count": 59
  },
  {
    "time": 140,
    "count": 35
  },
  {
    "time": 150,
    "count": 30
  },
  {
    "time": 160,
    "count": 34
  },
  {
    "time": 170,
    "count": 48
  },
  {
    "time": 180,
    "count": 30
  },
  {
    "time": 190,
    "count": 15
  },
  {
    "time": 200,
    "count": 24
  },
  {
    "time": 210,
    "count": 17
  },
  {
    "time": 220,
    "count": 16
  },
  {
    "time": 230,
    "count": 14
  },
  {
    "time": 240,
    "count": 12
  },
  {
    "time": 250,
    "count": 12
  },
  {
    "time": 260,
    "count": 11
  },
  {
    "time": 270,
    "count": 15
  },
  {
    "time": 280,
    "count": 7
  },
  {
    "time": 290,
    "count": 12
  },
  {
    "time": 300,
    "count": 13
  },
  {
    "time": 310,
    "count": 14
  },
  {
    "time": 320,
    "count": 25
  },
  {
    "time": 330,
    "count": 22
  },
  {
    "time": 340,
    "count": 19
  },
  {
    "time": 350,
    "count": 35
  },
  {
    "time": 360,
    "count": 31
  },
  {
    "time": 370,
    "count": 31
  },
  {
    "time": 380,
    "count": 28
  },
  {
    "time": 390,
    "count": 30
  },
  {
    "time": 400,
    "count": 32
  },
  {
    "time": 410,
    "count": 14
  },
  {
    "time": 420,
    "count": 10
  },
  {
    "time": 430,
    "count": 18
  },
  {
    "time": 440,
    "count": 17
  },
  {
    "time": 450,
    "count": 23
  },
  {
    "time": 460,
    "count": 19
  },
  {
    "time": 470,
    "count": 23
  },
  {
    "time": 480,
    "count": 16
  },
  {
    "time": 490,
    "count": 46
  },
  {
    "time": 500,
    "count": 121
  },
  {
    "time": 510,
    "count": 76
  },
  {
    "time": 520,
    "count": 47
  },
  {
    "time": 530,
    "count": 38
  },
  {
    "time": 540,
    "count": 23
  },
  {
    "time": 550,
    "count": 19
  },
  {
    "time": 560,
    "count": 7
  },
  {
    "time": 570,
    "count": 20
  },
  {
    "time": 580,
    "count": 49
  },
  {
    "time": 590,
    "count": 24
  },
  {
    "time": 600,
    "count": 33
  },
  {
    "time": 610,
    "count": 66
  },
  {
    "time": 620,
    "count": 63
  },
  {
    "time": 630,
    "count": 21
  },
  {
    "time": 640,
    "count": 21
  },
  {
    "time": 650,
    "count": 16
  },
  {
    "time": 660,
    "count": 30
  },
  {
    "time": 670,
    "count": 44
  },
  {
    "time": 680,
    "count": 38
  },
  {
    "time": 690,
    "count": 18
  },
  {
    "time": 700,
    "count": 8
  },
  {
    "time": 710,
    "count": 5
  },
  {
    "time": 720,
    "count": 9
  },
  {
    "time": 730,
    "count": 9
  },
  {
    "time": 740,
    "count": 8
  },
  {
    "time": 750,
    "count": 30
  },
  {
    "time": 760,
    "count": 34
  },
  {
    "time": 770,
    "count": 37
  },
  {
    "time": 780,
    "count": 32
  },
  {
    "time": 790,
    "count": 16
  },
  {
    "time": 800,
    "count": 14
  },
  {
    "time": 810,
    "count": 8
  },
  {
    "time": 820,
    "count": 7
  },
  {
    "time": 830,
    "count": 15
  },
  {
    "time": 840,
    "count": 16
  },
  {
    "time": 850,
    "count": 19
  },
  {
    "time": 860,
    "count": 12
  },
  {
    "time": 870,
    "count": 8
  },
  {
    "time": 880,
    "count": 9
  },
  {
    "time": 890,
    "count": 7
  },
  {
    "time": 900,
    "count": 4
  },
  {
    "time": 910,
    "count": 8
  },
  {
    "time": 920,
    "count": 23
  },
  {
    "time": 930,
    "count": 42
  },
  {
    "time": 940,
    "count": 33
  },
  {
    "time": 950,
    "count": 33
  },
  {
    "time": 960,
    "count": 15
  },
  {
    "time": 970,
    "count": 9
  },
  {
    "time": 980,
    "count": 16
  },
  {
    "time": 990,
    "count": 19
  },
  {
    "time": 1000,
    "count": 27
  },
  {
    "time": 1010,
    "count": 12
  },
  {
    "time": 1020,
    "count": 21
  },
  {
    "time": 1030,
    "count": 47
  },
  {
    "time": 1040,
    "count": 21
  },
  {
    "time": 1050,
    "count": 25
  },
  {
    "time": 1060,
    "count": 13
  },
  {
    "time": 1070,
    "count": 14
  },
  {
    "time": 1080,
    "count": 11
  },
  {
    "time": 1090,
    "count": 14
  },
  {
    "time": 1100,
    "count": 20
  },
  {
    "time": 1110,
    "count": 23
  },
  {
    "time": 1120,
    "count": 19
  },
  {
    "time": 1130,
    "count": 24
  },
  {
    "time": 1140,
    "count": 14
  },
  {
    "time": 1150,
    "count": 17
  },
  {
    "time": 1160,
    "count": 8
  },
  {
    "time": 1170,
    "count": 24
  },
  {
    "time": 1180,
    "count": 81
  },
  {
    "time": 1190,
    "count": 60
  },
  {
    "time": 1200,
    "count": 23
  },
  {
    "time": 1210,
    "count": 14
  },
  {
    "time": 1220,
    "count": 36
  },
  {
    "time": 1230,
    "count": 43
  },
  {
    "time": 1240,
    "count": 46
  },
  {
    "time": 1250,
    "count": 39
  },
  {
    "time": 1260,
    "count": 20
  },
  {
    "time": 1270,
    "count": 12
  },
  {
    "time": 1280,
    "count": 10
  },
  {
    "time": 1290,
    "count": 9
  },
  {
    "time": 1300,
    "count": 16
  },
  {
    "time": 1310,
    "count": 16
  },
  {
    "time": 1320,
    "count": 30
  },
  {
    "time": 1330,
    "count": 28
  },
  {
    "time": 1340,
    "count": 8
  },
  {
    "time": 1350,
    "count": 15
  },
  {
    "time": 1360,
    "count": 17
  },
  {
    "time": 1370,
    "count": 11
  },
  {
    "time": 1380,
    "count": 15
  },
  {
    "time": 1390,
    "count": 28
  },
  {
    "time": 1400,
    "count": 12
  },
  {
    "time": 1410,
    "count": 6
  },
  {
    "time": 1420,
    "count": 8
  },
  {
    "time": 1430,
    "count": 17
  },
  {
    "time": 1440,
    "count": 26
  },
  {
    "time": 1450,
    "count": 35
  },
  {
    "time": 1460,
    "count": 24
  },
  {
    "time": 1470,
    "count": 20
  },
  {
    "time": 1480,
    "count": 22
  },
  {
    "time": 1490,
    "count": 15
  },
  {
    "time": 1500,
    "count": 17
  },
  {
    "time": 1510,
    "count": 26
  },
  {
    "time": 1520,
    "count": 20
  },
  {
    "time": 1530,
    "count": 13
  },
  {
    "time": 1540,
    "count": 17
  },
  {
    "time": 1550,
    "count": 29
  },
  {
    "time": 1560,
    "count": 25
  },
  {
    "time": 1570,
    "count": 22
  },
  {
    "time": 1580,
    "count": 18
  },
  {
    "time": 1590,
    "count": 25
  },
  {
    "time": 1600,
    "count": 18
  },
  {
    "time": 1610,
    "count": 19
  },
  {
    "time": 1620,
    "count": 20
  },
  {
    "time": 1630,
    "count": 19
  },
  {
    "time": 1640,
    "count": 9
  },
  {
    "time": 1650,
    "count": 20
  },
  {
    "time": 1660,
    "count": 47
  },
  {
    "time": 1670,
    "count": 39
  },
  {
    "time": 1680,
    "count": 23
  },
  {
    "time": 1690,
    "count": 14
  },
  {
    "time": 1700,
    "count": 28
  },
  {
    "time": 1710,
    "count": 31
  },
  {
    "time": 1720,
    "count": 44
  },
  {
    "time": 1730,
    "count": 47
  },
  {
    "time": 1740,
    "count": 84
  },
  {
    "time": 1750,
    "count": 67
  },
  {
    "time": 1760,
    "count": 60
  },
  {
    "time": 1770,
    "count": 36
  },
  {
    "time": 1780,
    "count": 26
  },
  {
    "time": 1790,
    "count": 19
  },
  {
    "time": 1800,
    "count": 64
  },
  {
    "time": 1810,
    "count": 39
  },
  {
    "time": 1820,
    "count": 21
  },
  {
    "time": 1830,
    "count": 31
  },
  {
    "time": 1840,
    "count": 28
  },
  {
    "time": 1850,
    "count": 12
  },
  {
    "time": 1860,
    "count": 26
  },
  {
    "time": 1870,
    "count": 8
  },
  {
    "time": 1880,
    "count": 15
  },
  {
    "time": 1890,
    "count": 13
  },
  {
    "time": 1900,
    "count": 19
  },
  {
    "time": 1910,
    "count": 23
  },
  {
    "time": 1920,
    "count": 21
  },
  {
    "time": 1930,
    "count": 17
  },
  {
    "time": 1940,
    "count": 13
  },
  {
    "time": 1950,
    "count": 23
  },
  {
    "time": 1960,
    "count": 19
  },
  {
    "time": 1970,
    "count": 7
  },
  {
    "time": 1980,
    "count": 3
  },
  {
    "time": 1990,
    "count": 6
  },
  {
    "time": 2000,
    "count": 3
  },
  {
    "time": 2010,
    "count": 23
  },
  {
    "time": 2020,
    "count": 44
  },
  {
    "time": 2030,
    "count": 49
  },
  {
    "time": 2040,
    "count": 27
  },
  {
    "time": 2050,
    "count": 14
  },
  {
    "time": 2060,
    "count": 7
  },
  {
    "time": 2070,
    "count": 12
  },
  {
    "time": 2080,
    "count": 6
  },
  {
    "time": 2090,
    "count": 5
  },
  {
    "time": 2100,
    "count": 2
  },
  {
    "time": 2110,
    "count": 14
  },
  {
    "time": 2120,
    "count": 15
  },
  {
    "time": 2130,
    "count": 10
  },
  {
    "time": 2140,
    "count": 20
  },
  {
    "time": 2150,
    "count": 45
  },
  {
    "time": 2160,
    "count": 61
  },
  {
    "time": 2170,
    "count": 24
  },
  {
    "time": 2180,
    "count": 21
  },
  {
    "time": 2190,
    "count": 15
  },
  {
    "time": 2200,
    "count": 32
  },
  {
    "time": 2210,
    "count": 27
  },
  {
    "time": 2220,
    "count": 23
  },
  {
    "time": 2230,
    "count": 47
  },
  {
    "time": 2240,
    "count": 51
  },
  {
    "time": 2250,
    "count": 59
  },
  {
    "time": 2260,
    "count": 88
  },
  {
    "time": 2270,
    "count": 85
  },
  {
    "time": 2280,
    "count": 60
  },
  {
    "time": 2290,
    "count": 60
  },
  {
    "time": 2300,
    "count": 33
  },
  {
    "time": 2310,
    "count": 26
  },
  {
    "time": 2320,
    "count": 21
  },
  {
    "time": 2330,
    "count": 67
  },
  {
    "time": 2340,
    "count": 69
  },
  {
    "time": 2350,
    "count": 53
  },
  {
    "time": 2360,
    "count": 56
  },
  {
    "time": 2370,
    "count": 55
  },
  {
    "time": 2380,
    "count": 86
  },
  {
    "time": 2390,
    "count": 64
  },
  {
    "time": 2400,
    "count": 26
  },
  {
    "time": 2410,
    "count": 25
  },
  {
    "time": 2420,
    "count": 15
  },
  {
    "time": 2430,
    "count": 11
  },
  {
    "time": 2440,
    "count": 15
  },
  {
    "time": 2450,
    "count": 8
  },
  {
    "time": 2460,
    "count": 11
  },
  {
    "time": 2470,
    "count": 17
  },
  {
    "time": 2480,
    "count": 6
  },
  {
    "time": 2490,
    "count": 10
  },
  {
    "time": 2500,
    "count": 21
  },
  {
    "time": 2510,
    "count": 25
  },
  {
    "time": 2520,
    "count": 29
  },
  {
    "time": 2530,
    "count": 36
  },
  {
    "time": 2540,
    "count": 25
  },
  {
    "time": 2550,
    "count": 17
  },
  {
    "time": 2560,
    "count": 11
  },
  {
    "time": 2570,
    "count": 14
  },
  {
    "time": 2580,
    "count": 18
  },
  {
    "time": 2590,
    "count": 15
  },
  {
    "time": 2600,
    "count": 18
  },
  {
    "time": 2610,
    "count": 12
  },
  {
    "time": 2620,
    "count": 16
  },
  {
    "time": 2630,
    "count": 11
  },
  {
    "time": 2640,
    "count": 27
  },
  {
    "time": 2650,
    "count": 29
  },
  {
    "time": 2660,
    "count": 31
  },
  {
    "time": 2670,
    "count": 36
  },
  {
    "time": 2680,
    "count": 30
  },
  {
    "time": 2690,
    "count": 61
  },
  {
    "time": 2700,
    "count": 54
  },
  {
    "time": 2710,
    "count": 34
  },
  {
    "time": 2720,
    "count": 22
  },
  {
    "time": 2730,
    "count": 20
  },
  {
    "time": 2740,
    "count": 16
  },
  {
    "time": 2750,
    "count": 6
  },
  {
    "time": 2760,
    "count": 7
  },
  {
    "time": 2770,
    "count": 12
  },
  {
    "time": 2780,
    "count": 16
  },
  {
    "time": 2790,
    "count": 9
  },
  {
    "time": 2800,
    "count": 2
  },
  {
    "time": 2810,
    "count": 34
  },
  {
    "time": 2820,
    "count": 31
  },
  {
    "time": 2830,
    "count": 41
  },
  {
    "time": 2840,
    "count": 69
  },
  {
    "time": 2850,
    "count": 31
  },
  {
    "time": 2860,
    "count": 23
  },
  {
    "time": 2870,
    "count": 15
  },
  {
    "time": 2880,
    "count": 31
  },
  {
    "time": 2890,
    "count": 14
  },
  {
    "time": 2900,
    "count": 5
  },
  {
    "time": 2910,
    "count": 2
  },
  {
    "time": 2920,
    "count": 17
  },
  {
    "time": 2930,
    "count": 23
  },
  {
    "time": 2940,
    "count": 27
  },
  {
    "time": 2950,
    "count": 28
  },
  {
    "time": 2960,
    "count": 17
  },
  {
    "time": 2970,
    "count": 19
  },
  {
    "time": 2980,
    "count": 72
  },
  {
    "time": 2990,
    "count": 62
  },
  {
    "time": 3000,
    "count": 26
  },
  {
    "time": 3010,
    "count": 13
  },
  {
    "time": 3020,
    "count": 13
  },
  {
    "time": 3030,
    "count": 26
  },
  {
    "time": 3040,
    "count": 49
  },
  {
    "time": 3050,
    "count": 51
  },
  {
    "time": 3060,
    "count": 39
  },
  {
    "time": 3070,
    "count": 24
  },
  {
    "time": 3080,
    "count": 77
  },
  {
    "time": 3090,
    "count": 43
  },
  {
    "time": 3100,
    "count": 30
  },
  {
    "time": 3110,
    "count": 10
  },
  {
    "time": 3120,
    "count": 10
  },
  {
    "time": 3130,
    "count": 13
  },
  {
    "time": 3140,
    "count": 22
  },
  {
    "time": 3150,
    "count": 20
  },
  {
    "time": 3160,
    "count": 22
  },
  {
    "time": 3170,
    "count": 26
  },
  {
    "time": 3180,
    "count": 39
  },
  {
    "time": 3190,
    "count": 45
  },
  {
    "time": 3200,
    "count": 68
  },
  {
    "time": 3210,
    "count": 40
  },
  {
    "time": 3220,
    "count": 42
  },
  {
    "time": 3230,
    "count": 48
  },
  {
    "time": 3240,
    "count": 44
  },
  {
    "time": 3250,
    "count": 47
  },
  {
    "time": 3260,
    "count": 30
  },
  {
    "time": 3270,
    "count": 23
  },
  {
    "time": 3280,
    "count": 18
  },
  {
    "time": 3290,
    "count": 45
  },
  {
    "time": 3300,
    "count": 44
  },
  {
    "time": 3310,
    "count": 11
  },
  {
    "time": 3320,
    "count": 16
  },
  {
    "time": 3330,
    "count": 15
  },
  {
    "time": 3340,
    "count": 13
  },
  {
    "time": 3350,
    "count": 18
  },
  {
    "time": 3360,
    "count": 15
  },
  {
    "time": 3370,
    "count": 24
  },
  {
    "time": 3380,
    "count": 27
  },
  {
    "time": 3390,
    "count": 20
  },
  {
    "time": 3400,
    "count": 18
  },
  {
    "time": 3410,
    "count": 42
  },
  {
    "time": 3420,
    "count": 55
  },
  {
    "time": 3430,
    "count": 23
  },
  {
    "time": 3440,
    "count": 38
  },
  {
    "time": 3450,
    "count": 27
  },
  {
    "time": 3460,
    "count": 22
  },
  {
    "time": 3470,
    "count": 37
  },
  {
    "time": 3480,
    "count": 59
  },
  {
    "time": 3490,
    "count": 39
  },
  {
    "time": 3500,
    "count": 23
  },
  {
    "time": 3510,
    "count": 27
  },
  {
    "time": 3520,
    "count": 40
  },
  {
    "time": 3530,
    "count": 31
  },
  {
    "time": 3540,
    "count": 18
  },
  {
    "time": 3550,
    "count": 13
  },
  {
    "time": 3560,
    "count": 8
  },
  {
    "time": 3570,
    "count": 19
  },
  {
    "time": 3580,
    "count": 16
  },
  {
    "time": 3590,
    "count": 27
  },
  {
    "time": 3600,
    "count": 40
  },
  {
    "time": 3610,
    "count": 34
  },
  {
    "time": 3620,
    "count": 32
  },
  {
    "time": 3630,
    "count": 36
  },
  {
    "time": 3640,
    "count": 49
  },
  {
    "time": 3650,
    "count": 45
  },
  {
    "time": 3660,
    "count": 37
  },
  {
    "time": 3670,
    "count": 16
  },
  {
    "time": 3680,
    "count": 13
  },
  {
    "time": 3690,
    "count": 6
  },
  {
    "time": 3700,
    "count": 6
  },
  {
    "time": 3710,
    "count": 4
  },
  {
    "time": 3720,
    "count": 15
  },
  {
    "time": 3730,
    "count": 24
  },
  {
    "time": 3740,
    "count": 7
  },
  {
    "time": 3750,
    "count": 6
  },
  {
    "time": 3760,
    "count": 15
  },
  {
    "time": 3770,
    "count": 8
  },
  {
    "time": 3780,
    "count": 5
  },
  {
    "time": 3790,
    "count": 12
  },
  {
    "time": 3800,
    "count": 9
  },
  {
    "time": 3810,
    "count": 11
  },
  {
    "time": 3820,
    "count": 15
  },
  {
    "time": 3830,
    "count": 8
  },
  {
    "time": 3840,
    "count": 11
  },
  {
    "time": 3850,
    "count": 17
  },
  {
    "time": 3860,
    "count": 30
  },
  {
    "time": 3870,
    "count": 60
  },
  {
    "time": 3880,
    "count": 86
  },
  {
    "time": 3890,
    "count": 79
  },
  {
    "time": 3900,
    "count": 24
  },
  {
    "time": 3910,
    "count": 12
  },
  {
    "time": 3920,
    "count": 10
  },
  {
    "time": 3930,
    "count": 7
  },
  {
    "time": 3940,
    "count": 8
  },
  {
    "time": 3950,
    "count": 10
  },
  {
    "time": 3960,
    "count": 12
  },
  {
    "time": 3970,
    "count": 9
  },
  {
    "time": 3980,
    "count": 4
  },
  {
    "time": 3990,
    "count": 23
  },
  {
    "time": 4000,
    "count": 15
  },
  {
    "time": 4010,
    "count": 11
  },
  {
    "time": 4020,
    "count": 9
  },
  {
    "time": 4030,
    "count": 9
  },
  {
    "time": 4040,
    "count": 7
  },
  {
    "time": 4050,
    "count": 14
  },
  {
    "time": 4060,
    "count": 16
  },
  {
    "time": 4070,
    "count": 16
  },
  {
    "time": 4080,
    "count": 37
  },
  {
    "time": 4090,
    "count": 58
  },
  {
    "time": 4100,
    "count": 34
  },
  {
    "time": 4110,
    "count": 12
  },
  {
    "time": 4120,
    "count": 12
  },
  {
    "time": 4130,
    "count": 11
  },
  {
    "time": 4140,
    "count": 55
  },
  {
    "time": 4150,
    "count": 39
  },
  {
    "time": 4160,
    "count": 16
  },
  {
    "time": 4170,
    "count": 7
  },
  {
    "time": 4180,
    "count": 1
  },
  {
    "time": 4190,
    "count": 31
  },
  {
    "time": 4200,
    "count": 69
  },
  {
    "time": 4210,
    "count": 49
  },
  {
    "time": 4220,
    "count": 22
  },
  {
    "time": 4230,
    "count": 25
  },
  {
    "time": 4240,
    "count": 12
  },
  {
    "time": 4250,
    "count": 7
  },
  {
    "time": 4260,
    "count": 6
  },
  {
    "time": 4270,
    "count": 8
  },
  {
    "time": 4280,
    "count": 7
  },
  {
    "time": 4290,
    "count": 7
  },
  {
    "time": 4300,
    "count": 5
  },
  {
    "time": 4310,
    "count": 17
  },
  {
    "time": 4320,
    "count": 30
  },
  {
    "time": 4330,
    "count": 18
  },
  {
    "time": 4340,
    "count": 9
  },
  {
    "time": 4350,
    "count": 11
  },
  {
    "time": 4360,
    "count": 15
  },
  {
    "time": 4370,
    "count": 20
  },
  {
    "time": 4380,
    "count": 10
  },
  {
    "time": 4390,
    "count": 41
  },
  {
    "time": 4400,
    "count": 18
  },
  {
    "time": 4410,
    "count": 42
  },
  {
    "time": 4420,
    "count": 26
  },
  {
    "time": 4430,
    "count": 17
  },
  {
    "time": 4440,
    "count": 7
  },
  {
    "time": 4450,
    "count": 18
  },
  {
    "time": 4460,
    "count": 9
  },
  {
    "time": 4470,
    "count": 10
  },
  {
    "time": 4480,
    "count": 14
  },
  {
    "time": 4490,
    "count": 12
  },
  {
    "time": 4500,
    "count": 12
  },
  {
    "time": 4510,
    "count": 5
  },
  {
    "time": 4520,
    "count": 14
  },
  {
    "time": 4530,
    "count": 16
  },
  {
    "time": 4540,
    "count": 26
  },
  {
    "time": 4550,
    "count": 57
  },
  {
    "time": 4560,
    "count": 39
  },
  {
    "time": 4570,
    "count": 31
  },
  {
    "time": 4580,
    "count": 39
  },
  {
    "time": 4590,
    "count": 24
  },
  {
    "time": 4600,
    "count": 10
  },
  {
    "time": 4610,
    "count": 34
  },
  {
    "time": 4620,
    "count": 27
  },
  {
    "time": 4630,
    "count": 18
  },
  {
    "time": 4640,
    "count": 6
  },
  {
    "time": 4650,
    "count": 3
  },
  {
    "time": 4660,
    "count": 5
  },
  {
    "time": 4670,
    "count": 9
  },
  {
    "time": 4680,
    "count": 3
  },
  {
    "time": 4690,
    "count": 5
  },
  {
    "time": 4700,
    "count": 7
  },
  {
    "time": 4710,
    "count": 11
  },
  {
    "time": 4720,
    "count": 17
  },
  {
    "time": 4730,
    "count": 28
  },
  {
    "time": 4740,
    "count": 11
  },
  {
    "time": 4750,
    "count": 11
  },
  {
    "time": 4760,
    "count": 10
  },
  {
    "time": 4770,
    "count": 7
  },
  {
    "time": 4780,
    "count": 11
  },
  {
    "time": 4790,
    "count": 4
  },
  {
    "time": 4800,
    "count": 4
  },
  {
    "time": 4810,
    "count": 10
  },
  {
    "time": 4820,
    "count": 5
  },
  {
    "time": 4830,
    "count": 8
  },
  {
    "time": 4840,
    "count": 15
  },
  {
    "time": 4850,
    "count": 23
  },
  {
    "time": 4860,
    "count": 18
  },
  {
    "time": 4870,
    "count": 7
  },
  {
    "time": 4880,
    "count": 3
  },
  {
    "time": 4890,
    "count": 4
  },
  {
    "time": 4900,
    "count": 4
  },
  {
    "time": 4910,
    "count": 2
  },
  {
    "time": 4920,
    "count": 13
  },
  {
    "time": 4930,
    "count": 10
  },
  {
    "time": 4940,
    "count": 3
  },
  {
    "time": 4950,
    "count": 4
  },
  {
    "time": 4960,
    "count": 13
  },
  {
    "time": 4970,
    "count": 17
  },
  {
    "time": 4980,
    "count": 11
  },
  {
    "time": 4990,
    "count": 7
  },
  {
    "time": 5000,
    "count": 12
  },
  {
    "time": 5010,
    "count": 16
  },
  {
    "time": 5020,
    "count": 44
  },
  {
    "time": 5030,
    "count": 56
  },
  {
    "time": 5040,
    "count": 29
  },
  {
    "time": 5050,
    "count": 22
  },
  {
    "time": 5060,
    "count": 9
  },
  {
    "time": 5070,
    "count": 54
  },
  {
    "time": 5080,
    "count": 14
  },
  {
    "time": 5090,
    "count": 4
  },
  {
    "time": 5100,
    "count": 1
  },
  {
    "time": 5110,
    "count": 2
  },
  {
    "time": 5120,
    "count": 2
  },
  {
    "time": 5130,
    "count": 7
  },
  {
    "time": 5140,
    "count": 6
  },
  {
    "time": 5150,
    "count": 5
  },
  {
    "time": 5160,
    "count": 9
  },
  {
    "time": 5170,
    "count": 7
  },
  {
    "time": 5180,
    "count": 7
  },
  {
    "time": 5190,
    "count": 11
  },
  {
    "time": 5200,
    "count": 36
  },
  {
    "time": 5210,
    "count": 24
  },
  {
    "time": 5220,
    "count": 9
  },
  {
    "time": 5230,
    "count": 3
  },
  {
    "time": 5240,
    "count": 8
  },
  {
    "time": 5250,
    "count": 12
  },
  {
    "time": 5260,
    "count": 6
  },
  {
    "time": 5270,
    "count": 10
  },
  {
    "time": 5280,
    "count": 3
  },
  {
    "time": 5290,
    "count": 2
  },
  {
    "time": 5300,
    "count": 13
  },
  {
    "time": 5310,
    "count": 24
  },
  {
    "time": 5320,
    "count": 42
  },
  {
    "time": 5330,
    "count": 22
  },
  {
    "time": 5340,
    "count": 4
  },
  {
    "time": 5350,
    "count": 9
  },
  {
    "time": 5360,
    "count": 19
  },
  {
    "time": 5370,
    "count": 5
  },
  {
    "time": 5380,
    "count": 3
  },
  {
    "time": 5390,
    "count": 11
  },
  {
    "time": 5400,
    "count": 32
  },
  {
    "time": 5410,
    "count": 101
  },
  {
    "time": 5420,
    "count": 89
  },
  {
    "time": 5430,
    "count": 43
  },
  {
    "time": 5440,
    "count": 30
  },
  {
    "time": 5450,
    "count": 31
  },
  {
    "time": 5460,
    "count": 100
  },
  {
    "time": 5470,
    "count": 108
  },
  {
    "time": 5480,
    "count": 94
  },
  {
    "time": 5490,
    "count": 76
  },
  {
    "time": 5500,
    "count": 47
  },
  {
    "time": 5510,
    "count": 28
  },
  {
    "time": 5520,
    "count": 6
  },
  {
    "time": 5530,
    "count": 0
  }
]